skilleter_tfm/__init__.py
skilleter_tfm/tfm.py
skilleter_tfm/tfm_pane.py
skilleter_tfm-0.0.10.dist-info/licenses/LICENSE
skilleter_tfm-0.0.10.dist-info/METADATA
skilleter_tfm-0.0.10.dist-info/WHEEL
skilleter_tfm-0.0.10.dist-info/entry_points.txt
skilleter_tfm-0.0.10.dist-info/top_level.txt
skilleter_tfm-0.0.10.dist-info/RECORD
