Metadata-Version: 2.4
Name: skilleter-tfm
Version: 0.0.10
Summary: Console file manager
Author-email: John Skilleter <john@skilleter.org.uk>
Project-URL: Home, https://skilleter.org.uk
Project-URL: Repository, https://gitlab.com/skilleter/skilleter-tfm
Project-URL: Issues, https://gitlab.com/skilleter/skilleter-tfm/-/issues
Classifier: Programming Language :: Python :: 3
Classifier: License :: OSI Approved :: GNU General Public License v3 or later (GPLv3+)
Classifier: Operating System :: OS Independent
Requires-Python: >=3.9
License-File: LICENSE
Requires-Dist: skilleter-modules>=0.0.7
Requires-Dist: inotify
Dynamic: license-file
